<?xml version="1.0" encoding="utf-8"?>
<!--XSLT Processor: Apache Software Foundation-->
<document-summary uri="http://www.w3.org/TR/xslt-xquery-serialization/">
<title>XSLT and XQuery Serialization</title>
<div1 id="intro">
<head>
1 Introduction</head>
<div2 id="terminology">
<head>
1.1 Terminology</head>
</div2>
</div1>
<div1 id="serdm">
<head>
2 Sequence Normalization</head>
</div1>
<div1 id="serparam">
<head>
3 Serialization Parameters</head>
</div1>
<div1 id="serphases">
<head>
4 Phases of Serialization</head>
</div1>
<div1 id="xml-output">
<head>
5 XML Output Method</head>
<div2 id="XML_PARAMS">
<head>
5.1 The Influence of Serialization Parameters upon the XML Output Method</head>
<div3 id="XML_VERSION">
<head>
5.1.1 XML Output Method: the version Parameter</head>
</div3>
<div3 id="XML_ENCODING">
<head>
5.1.2 XML Output Method: the encoding Parameter</head>
</div3>
<div3 id="xml-indent">
<head>
5.1.3 XML Output Method: the indent and suppress-indentation Parameters</head>
</div3>
<div3 id="XML_CDATA-SECTION-ELEMENTS">
<head>
5.1.4 XML Output Method: the cdata-section-elements Parameter</head>
</div3>
<div3 id="XML_OMIT-XML-DECLARATION">
<head>
5.1.5 XML Output Method: the omit-xml-declaration and standalone Parameters</head>
</div3>
<div3 id="XML_DOCTYPE">
<head>
5.1.6 XML Output Method: the doctype-system and doctype-public Parameters</head>
</div3>
<div3 id="xml-undeclare-NS">
<head>
5.1.7 XML Output Method: the undeclare-prefixes Parameter</head>
</div3>
<div3 id="XML_NORMALIZATION-FORM">
<head>
5.1.8 XML Output Method: the normalization-form Parameter</head>
</div3>
<div3 id="XML_MEDIA-TYPE">
<head>
5.1.9 XML Output Method: the media-type Parameter</head>
</div3>
<div3 id="XML_USE-CHARACTER-MAPS">
<head>
5.1.10 XML Output Method: the use-character-maps Parameter</head>
</div3>
<div3 id="XML_BYTE-ORDER-MARK">
<head>
5.1.11 XML Output Method: the byte-order-mark Parameter</head>
</div3>
<div3 id="XML_ESCAPE-URI-ATTRIBUTES">
<head>
5.1.12 XML Output Method: the escape-uri-attributes Parameter</head>
</div3>
<div3 id="XML_INCLUDE-CONTENT-TYPE">
<head>
5.1.13 XML Output Method: the include-content-type Parameter</head>
</div3>
</div2>
</div1>
<div1 id="xhtml-output">
<head>
6 XHTML Output Method</head>
<div2 id="XHTML_PARAMS">
<head>
6.1 The Influence of Serialization Parameters upon the XHTML Output Method</head>
<div3 id="XHTML_VERSION">
<head>
6.1.1 XHTML Output Method: the version Parameter</head>
</div3>
<div3 id="XHTML_ENCODING">
<head>
6.1.2 XHTML Output Method: the encoding Parameter</head>
</div3>
<div3 id="XHTML_INDENT">
<head>
6.1.3 XHTML Output Method: the indent and suppress-indentation Parameters</head>
</div3>
<div3 id="XHTML_CDATA-SECTION-ELEMENTS">
<head>
6.1.4 XHTML Output Method: the cdata-section-elements Parameter</head>
</div3>
<div3 id="XHTML_OMIT-XML-DECLARATION">
<head>
6.1.5 XHTML Output Method: the omit-xml-declaration and standalone Parameters</head>
</div3>
<div3 id="XHTML_DOCTYPE">
<head>
6.1.6 XHTML Output Method: the doctype-system and doctype-public Parameters</head>
</div3>
<div3 id="XHTML_UNDECLARE-PREFIXES">
<head>
6.1.7 XHTML Output Method: the undeclare-prefixes Parameter</head>
</div3>
<div3 id="XHTML_NORMALIZATION-FORM">
<head>
6.1.8 XHTML Output Method: the normalization-form Parameter</head>
</div3>
<div3 id="XHTML_MEDIA-TYPE">
<head>
6.1.9 XHTML Output Method: the media-type Parameter</head>
</div3>
<div3 id="XHTML_USE-CHARACTER-MAPS">
<head>
6.1.10 XHTML Output Method: the use-character-maps Parameter</head>
</div3>
<div3 id="XHTML_BYTE-ORDER-MARK">
<head>
6.1.11 XHTML Output Method: the byte-order-mark Parameter</head>
</div3>
<div3 id="XHTML_ESCAPE-URI-ATTRIBUTES">
<head>
6.1.12 XHTML Output Method: the escape-uri-attributes Parameter</head>
</div3>
<div3 id="XHTML_INCLUDE-CONTENT-TYPE">
<head>
6.1.13 XHTML Output Method: the include-content-type Parameter</head>
</div3>
</div2>
</div1>
<div1 id="html-output">
<head>
7 HTML Output Method</head>
<div2 id="HTML_MARKUP">
<head>
7.1 Markup for Elements</head>
</div2>
<div2 id="HTML_ATTRIBS">
<head>
7.2 Writing Attributes</head>
</div2>
<div2 id="HTML_CHARDATA">
<head>
7.3 Writing Character Data</head>
</div2>
<div2 id="HTML_PARAMS">
<head>
7.4 The Influence of Serialization Parameters upon the HTML Output Method</head>
<div3 id="HTML_VERSION">
<head>
7.4.1 HTML Output Method: the version Parameter</head>
</div3>
<div3 id="HTML_ENCODING">
<head>
7.4.2 HTML Output Method: the encoding Parameter</head>
</div3>
<div3 id="HTML_INDENT">
<head>
7.4.3 HTML Output Method: the indent and suppress-indentation Parameters</head>
</div3>
<div3 id="HTML_CDATA-SECTION-ELEMENTS">
<head>
7.4.4 HTML Output Method: the cdata-section-elements Parameter</head>
</div3>
<div3 id="HTML_OMIT-XML-DECLARATION">
<head>
7.4.5 HTML Output Method: the omit-xml-declaration and standalone Parameters</head>
</div3>
<div3 id="HTML_DOCTYPE">
<head>
7.4.6 HTML Output Method: the doctype-system and doctype-public Parameters</head>
</div3>
<div3 id="HTML_UNDECLARE-PREFIXES">
<head>
7.4.7 HTML Output Method: the undeclare-prefixes Parameter</head>
</div3>
<div3 id="HTML_NORMALIZATION-FORM">
<head>
7.4.8 HTML Output Method: the normalization-form Parameter</head>
</div3>
<div3 id="HTML_MEDIA-TYPE">
<head>
7.4.9 HTML Output Method: the media-type Parameter</head>
</div3>
<div3 id="HTML_USE-CHARACTER-MAPS">
<head>
7.4.10 HTML Output Method: the use-character-maps Parameter</head>
</div3>
<div3 id="HTML_BYTE-ORDER-MARK">
<head>
7.4.11 HTML Output Method: the byte-order-mark Parameter</head>
</div3>
<div3 id="HTML_ESCAPE-URI-ATTRIBUTES">
<head>
7.4.12 HTML Output Method: the escape-uri-attributes Parameter</head>
</div3>
<div3 id="HTML_INCLUDE-CONTENT-TYPE">
<head>
7.4.13 HTML Output Method: the include-content-type Parameter</head>
</div3>
</div2>
</div1>
<div1 id="text-output">
<head>
8 Text Output Method</head>
<div2 id="TEXT_PARAMS">
<head>
8.1 The Influence of Serialization Parameters upon the Text Output Method</head>
<div3 id="TEXT_VERSION">
<head>
8.1.1 Text Output Method: the version Parameter</head>
</div3>
<div3 id="TEXT_ENCODING">
<head>
8.1.2 Text Output Method: the encoding Parameter</head>
</div3>
<div3 id="TEXT_INDENT">
<head>
8.1.3 Text Output Method: the indent and suppress-indentation Parameters</head>
</div3>
<div3 id="TEXT_CDATA-SECTION-ELEMENTS">
<head>
8.1.4 Text Output Method: the cdata-section-elements Parameter</head>
</div3>
<div3 id="TEXT_OMIT-XML-DECLARATION">
<head>
8.1.5 Text Output Method: the omit-xml-declaration and standalone Parameters</head>
</div3>
<div3 id="TEXT_DOCTYPE">
<head>
8.1.6 Text Output Method: the doctype-system and doctype-public Parameters</head>
</div3>
<div3 id="TEXT_UNDECLARE-PREFIXES">
<head>
8.1.7 Text Output Method: the undeclare-prefixes Parameter</head>
</div3>
<div3 id="TEXT_NORMALIZATION-FORM">
<head>
8.1.8 Text Output Method: the normalization-form Parameter</head>
</div3>
<div3 id="TEXT_MEDIA-TYPE">
<head>
8.1.9 Text Output Method: the media-type Parameter</head>
</div3>
<div3 id="TEXT_USE-CHARACTER-MAPS">
<head>
8.1.10 Text Output Method: the use-character-maps Parameter</head>
</div3>
<div3 id="TEXT_BYTE-ORDER-MARK">
<head>
8.1.11 Text Output Method: the byte-order-mark Parameter</head>
</div3>
<div3 id="TEXT_ESCAPE-URI-ATTRIBUTES">
<head>
8.1.12 Text Output Method: the escape-uri-attributes Parameter</head>
</div3>
<div3 id="TEXT_INCLUDE-CONTENT-TYPE">
<head>
8.1.13 Text Output Method: the include-content-type Parameter</head>
</div3>
</div2>
</div1>
<div1 id="character-maps">
<head>
9 Character Maps</head>
</div1>
<div1 id="conformance">
<head>
10 Conformance</head>
</div1>
<div1 id="references">
<head>
A References</head>
<div2 id="normative-references">
<head>
A.1 Normative References</head>
</div2>
<div2 id="informative-references">
<head>
A.2 Informative References</head>
</div2>
</div1>
<div1 id="id-errors">
<head>
B Summary of Error Conditions</head>
</div1>
<div1 id="list-of-uri-attributes">
<head>
C List of URI Attributes</head>
</div1>
<inform-div1 id="implementation-defined-features">
<head>
D Checklist of Implementation-Defined Features (Non-Normative)</head>
</inform-div1>
<inform-div1 id="revision-log">
<head>
E Revision Log (Non-Normative)</head>
</inform-div1>
<termdef xmlns:e="http://www.w3.org/1999/XSL/Spec/ElementSyntax" id="serializer" term="serializer"/>
<termdef xmlns:e="http://www.w3.org/1999/XSL/Spec/ElementSyntax" id="impdef" term="implementation-defined"/>
<termdef xmlns:e="http://www.w3.org/1999/XSL/Spec/ElementSyntax" id="impdep" term="implementation-dependent"/>
<termdef xmlns:e="http://www.w3.org/1999/XSL/Spec/ElementSyntax" id="serial-err" term="serialization error"/>
<termdef xmlns:e="http://www.w3.org/1999/XSL/Spec/ElementSyntax" id="dt-atomization" term="atomize"/>
<termdef xmlns:e="http://www.w3.org/1999/XSL/Spec/ElementSyntax" id="dt-node" term="node"/>
<termdef xmlns:e="http://www.w3.org/1999/XSL/Spec/ElementSyntax" id="dt-sequence" term="sequence"/>
<termdef xmlns:e="http://www.w3.org/1999/XSL/Spec/ElementSyntax" id="dt-function-item" term="function item"/>
<termdef xmlns:e="http://www.w3.org/1999/XSL/Spec/ElementSyntax" id="dt-string-value" term="string value"/>
<termdef xmlns:e="http://www.w3.org/1999/XSL/Spec/ElementSyntax" id="dt-expanded-qname" term="expanded QName"/>
<termdef xmlns:e="http://www.w3.org/1999/XSL/Spec/ElementSyntax" id="null-namespace-URI" term="null namespace URI"/>
<termdef xmlns:e="http://www.w3.org/1999/XSL/Spec/ElementSyntax" id="non-null-namespace-URI" term="non-null namespace URI"/>
<termdef xmlns:e="http://www.w3.org/1999/XSL/Spec/ElementSyntax" id="sequence-normalization" term="sequence normalization"/>
<termdef xmlns:e="http://www.w3.org/1999/XSL/Spec/ElementSyntax" term="result tree" id="result-tree"/>
<termdef xmlns:e="http://www.w3.org/1999/XSL/Spec/ElementSyntax" term="URI Escaping" id="uri-escaping"/>
<termdef xmlns:e="http://www.w3.org/1999/XSL/Spec/ElementSyntax" term="URI attribute values" id="uri-attribute-values"/>
<termdef xmlns:e="http://www.w3.org/1999/XSL/Spec/ElementSyntax" term="Unicode Normalization" id="unicode-normalization"/>
<termdef xmlns:e="http://www.w3.org/1999/XSL/Spec/ElementSyntax" id="reconstructed-tree" term="reconstructed tree"/>
<termdef xmlns:e="http://www.w3.org/1999/XSL/Spec/ElementSyntax" term="EMPTY" id="XHTMLEMPTY"/>
<termdef xmlns:e="http://www.w3.org/1999/XSL/Spec/ElementSyntax" id="XML-ISLAND" term="XML Island"/>
<termdef xmlns:e="http://www.w3.org/1999/XSL/Spec/ElementSyntax" term="host language" id="host-language"/>
<error xmlns:e="http://www.w3.org/1999/XSL/Spec/ElementSyntax" spec="SE" code="0001" class="NR" type="serialization"/>
<error xmlns:e="http://www.w3.org/1999/XSL/Spec/ElementSyntax" spec="SE" code="0003" class="RE" type="serialization"/>
<error xmlns:e="http://www.w3.org/1999/XSL/Spec/ElementSyntax" spec="SE" code="0004" class="PM" type="serialization"/>
<error xmlns:e="http://www.w3.org/1999/XSL/Spec/ElementSyntax" spec="SE" code="0005" class="RE" type="serialization"/>
<error xmlns:e="http://www.w3.org/1999/XSL/Spec/ElementSyntax" spec="SE" code="0006" class="RE" type="serialization"/>
<error xmlns:e="http://www.w3.org/1999/XSL/Spec/ElementSyntax" spec="SE" code="0007" class="SU" type="serialization"/>
<error xmlns:e="http://www.w3.org/1999/XSL/Spec/ElementSyntax" spec="SE" code="0008" class="RE" type="serialization"/>
<error xmlns:e="http://www.w3.org/1999/XSL/Spec/ElementSyntax" spec="SE" code="0009" class="PM" type="serialization"/>
<error xmlns:e="http://www.w3.org/1999/XSL/Spec/ElementSyntax" spec="SE" code="0010" class="PM" type="serialization"/>
<error xmlns:e="http://www.w3.org/1999/XSL/Spec/ElementSyntax" spec="SE" code="0011" class="SU" type="serialization"/>
<error xmlns:e="http://www.w3.org/1999/XSL/Spec/ElementSyntax" spec="SE" code="0012" class="RE" type="serialization"/>
<error xmlns:e="http://www.w3.org/1999/XSL/Spec/ElementSyntax" spec="SE" code="0013" class="SU" type="serialization"/>
<error xmlns:e="http://www.w3.org/1999/XSL/Spec/ElementSyntax" spec="SE" code="0014" class="RE" type="serialization"/>
<error xmlns:e="http://www.w3.org/1999/XSL/Spec/ElementSyntax" spec="SE" code="0015" class="RE" type="serialization"/>
<error xmlns:e="http://www.w3.org/1999/XSL/Spec/ElementSyntax" spec="SE" code="0016" class="PM" type="serialization"/>
</document-summary>
